{
  "docs": {
    "Basics": ["support", "architecture", "softwareengineering", "bootstrap", "devsecops"],
    "Development Environment": ["developmentenvironment", "account", "tools"],
    "Plattform": ["plattform", "iam", "events", "backend/persistance", "ai"],
    "Services": ["services", "backend/containers", "backend/python", "backend/testing"],
    "Frontend": ["frontend"],
    "Automation": ["datascience", "backend/chatbots"],
    "Learning": ["techstack"]
  },
  "docs-other": {
    "Introduction": ["adr"],
    "ADRs": ["adr/adr1", "adr/adr2", "adr/adr3", "adr/adr4", "adr/adr5", "adr/adr6", "adr/adr7", "adr/adr8", "adr/adr9"]
  }
}